Workbook

Sheet Round1
A1: STEP 1 | H1: Disc All | I1: Disc Sel | J1: Basic All | K1: Basic Sel | L1: Prem All | M1: Prem Sel | O1: Cost | V1: Mult
A2: Category | B2: Premium | C2: Standard | D2: Basic | E2: Discount | F2: Total | H2: Player 1 | I2: Player 2 | J2: Player 3 | K2: Player 4 | L2: Player 5 | M2: Player 6 | O2: Player 1 | P2: Player 2 | Q2: Player 3 | R2: Player 4 | S2: Player 5 | T2: Player 6 | V2: Player 1 | W2: Player 2 | X2: Player 3 | Y2: Player 4 | Z2: Player 5 | AA2: Player 6 | AB2: Local
A3: Food | B3: 600 | C3: 1250 | D3: 1300 | E3: 1800 | F3: =SUM(B3:E3) -> 4950 | H3: 1 | I3: 1 | J3: 1 | K3: 1 | L3: 1 | M3: 1
A4: Mobile | B4: 700 | C4: 800 | D4: 700 | E4: 900 | F4: =SUM(B4:E4) -> 3100 | H4: 1 | I4: 1 | J4: 1 | L4: 1
A5: Clothes | B5: 200 | C5: 500 | D5: 700 | E5: 1200 | F5: =SUM(B5:E5) -> 2600 | H5: 1 | J5: 1 | L5: 1 | M5: 1
A6: TOTAL | B6: =SUM(B3:B5) -> 1500 | C6: =SUM(C3:C5) -> 2550 | D6: =SUM(D3:D5) -> 2700 | E6: =SUM(E3:E5) -> 3900 | F6: =SUM(F3:F5) -> 10650
A9: STEP 2 | O9: =SUM(O11:O12) -> 115000 | P9: =SUM(P11:P12) -> 115000 | Q9: =SUM(Q11:Q12) -> 115000 | R9: =SUM(R11:R12) -> 115000 | S9: =SUM(S11:S12) -> 115000 | T9: =SUM(T11:T12) -> 115000
A10: Fleet | B10: Applies To | C10: Multiplier | D10: Cost | E10: Ratio | O10: =SUM(O13:O17) -> 105000 | P10: =SUM(P13:P17) -> 90000 | Q10: =SUM(Q13:Q17) -> 123000 | R10: =SUM(R13:R17) -> 125000 | S10: =SUM(S13:S17) -> 123000 | T10: =SUM(T13:T17) -> 105000 | V10: =PRODUCT(V13:V18) -> 1.16655 | W10: =PRODUCT(W13:W18) -> 1.13526 | X10: =PRODUCT(X13:X18) -> 1.16802 | Y10: =PRODUCT(Y13:Y18) -> 1.16844 | Z10: =PRODUCT(Z13:Z18) -> 1.16802 | AA10: =PRODUCT(AA13:AA18) -> 1.16865
A11: Number of riders | B11: Slider | D11: 30000 | H11: 3 | I11: 3 | J11: 3 | K11: 3 | L11: 3 | M11: 3 | O11: =H11*$D$11 -> 90000 | P11: =I11*$D$11 -> 90000 | Q11: =J11*$D$11 -> 90000 | R11: =K11*$D$11 -> 90000 | S11: =L11*$D$11 -> 90000 | T11: =M11*$D$11 -> 90000
A12: Number of bikes | B12: Slider | D12: 25000 | H12: 1 | I12: 1 | J12: 1 | K12: 1 | L12: 1 | M12: 1 | O12: =H12*$D$12 -> 25000 | P12: =I12*$D$12 -> 25000 | Q12: =J12*$D$12 -> 25000 | R12: =K12*$D$12 -> 25000 | S12: =L12*$D$12 -> 25000 | T12: =M12*$D$12 -> 25000
A13: Route Optimization | C13: 1.1 | D13: 100000 | E13: =100000*(C13-1)/D13 -> 0.1 | H13: 1 | O13: =H13*$D13 -> 100000 | P13: =I13*$D13 -> 0 | Q13: =J13*$D13 -> 0 | R13: =K13*$D13 -> 0 | S13: =L13*$D13 -> 0 | T13: =M13*$D13 -> 0 | V13: =IF(O13>0,$C13,1) -> 1.1 | W13: =IF(P13>0,$C13,1) -> 1 | X13: =IF(Q13>0,$C13,1) -> 1 | Y13: =IF(R13>0,$C13,1) -> 1 | Z13: =IF(S13>0,$C13,1) -> 1 | AA13: =IF(T13>0,$C13,1) -> 1
A14: GPS Tracking | B14: Premium, Standard | C14: 1.06 | D14: 80000 | E14: =100000*(C14-1)/D14 -> 0.075 | I14: 1 | M14: 1 | O14: =H14*D14 -> 0 | P14: =I14*$D14 -> 80000 | Q14: =J14*$D14 -> 0 | R14: =K14*$D14 -> 0 | S14: =L14*$D14 -> 0 | T14: =M14*$D14 -> 80000 | V14: =IF(O14>0,$C14,1) -> 1 | W14: =IF(P14>0,$C14,1) -> 1.06 | X14: =IF(Q14>0,$C14,1) -> 1 | Y14: =IF(R14>0,$C14,1) -> 1 | Z14: =IF(S14>0,$C14,1) -> 1 | AA14: =IF(T14>0,$C14,1) -> 1.06
A15: Algorithm Assignment | C15: 1.08 | D15: 108000 | E15: =100000*(C15-1)/D15 -> 0.074074074 | J15: 1 | L15: 1 | O15: =H15*D15 -> 0 | P15: =I15*$D15 -> 0 | Q15: =J15*$D15 -> 108000 | R15: =K15*$D15 -> 0 | S15: =L15*$D15 -> 108000 | T15: =M15*$D15 -> 0 | V15: =IF(O15>0,$C15,1) -> 1 | W15: =IF(P15>0,$C15,1) -> 1 | X15: =IF(Q15>0,$C15,1) -> 1.08 | Y15: =IF(R15>0,$C15,1) -> 1 | Z15: =IF(S15>0,$C15,1) -> 1.08 | AA15: =IF(T15>0,$C15,1) -> 1
A16: Warehousing System | C16: 1.07 | D16: 105000 | E16: =100000*(C16-1)/D16 -> 0.066666667 | K16: 1 | O16: =H16*D16 -> 0 | P16: =I16*$D16 -> 0 | Q16: =J16*$D16 -> 0 | R16: =K16*$D16 -> 105000 | S16: =L16*$D16 -> 0 | T16: =M16*$D16 -> 0 | V16: =IF(O16>0,$C16,1) -> 1 | W16: =IF(P16>0,$C16,1) -> 1 | X16: =IF(Q16>0,$C16,1) -> 1 | Y16: =IF(R16>0,$C16,1) -> 1.07 | Z16: =IF(S16>0,$C16,1) -> 1 | AA16: =IF(T16>0,$C16,1) -> 1
A17: Electric Bikes % | B17: Competitive | C17: 0.1 | D17: 2 | H17: 0.1 | I17: 0.2 | J17: 0.3 | K17: 0.4 | L17: 0.3 | M17: 0.5 | O17: =H17*H12*$D12*$D17 -> 5000 | P17: =I17*I12*$D12*$D17 -> 10000 | Q17: =J17*J12*$D12*$D17 -> 15000 | R17: =K17*K12*$D12*$D17 -> 20000 | S17: =L17*L12*$D12*$D17 -> 15000 | T17: =M17*M12*$D12*$D17 -> 25000 | V17: =1+(O17*$C17/($D17*$D12)) -> 1.01 | W17: =1+(P17*$C17/($D17*$D12)) -> 1.02 | X17: =1+(Q17*$C17/($D17*$D12)) -> 1.03 | Y17: =1+(R17*$C17/($D17*$D12)) -> 1.04 | Z17: =1+(S17*$C17/($D17*$D12)) -> 1.03 | AA17: =1+(T17*$C17/($D17*$D12)) -> 1.05
A18: Bike-Rider Optimization | B18: Indi Efficiency | C18: 0.85 | D18: 0.95 | E18: 1.05 | V18: =IF(H11/H12<$C19,$C18,IF(H11/H12>$D19,$D18,$E18)) -> 1.05 | W18: =IF(I11/I12<$C19,$C18,IF(I11/I12>$D19,$D18,$E18)) -> 1.05 | X18: =IF(J11/J12<$C19,$C18,IF(J11/J12>$D19,$D18,$E18)) -> 1.05 | Y18: =IF(K11/K12<$C19,$C18,IF(K11/K12>$D19,$D18,$E18)) -> 1.05 | Z18: =IF(L11/L12<$C19,$C18,IF(L11/L12>$D19,$D18,$E18)) -> 1.05 | AA18: =IF(M11/M12<$C19,$C18,IF(M11/M12>$D19,$D18,$E18)) -> 1.05
C19: 2.5 | D19: 3.5
A22: STEP 3
A23: Technology | B23: Applies To | C23: Multiplier | D23: Cost | E23: Ratio | O23: =SUM(O24:O31) -> 175000 | P23: =SUM(P24:P31) -> 150000 | Q23: =SUM(Q24:Q31) -> 213000 | R23: =SUM(R24:R31) -> 173500 | S23: =SUM(S24:S31) -> 305000 | T23: =SUM(T24:T31) -> 155000 | V23: =PRODUCT(V24:V32) -> 1.06605 | W23: =PRODUCT(W24:W32) -> 1.01124 | X23: =PRODUCT(X24:X32) -> 1.1772 | Y23: =PRODUCT(Y24:Y32) -> 1.02078 | Z23: =PRODUCT(Z24:Z32) -> 1.294048 | AA23: =PRODUCT(AA24:AA32) -> 1.03824
A24: Mobile App | B24: Mandatory | C24: 1.15 | D24: 140000 | E24: =100000*(C24-1)/D24 -> 0.10714286 | H24: 1 | O24: =H24*$D24 -> 140000 | P24: =I24*$D24 -> 0 | Q24: =J24*$D24 -> 0 | R24: =K24*$D24 -> 0 | S24: =L24*$D24 -> 0 | T24: =M24*$D24 -> 0 | V24: =IF(O24>0,$C24,1) -> 1.15 | W24: =IF(P24>0,$C24,1) -> 1 | X24: =IF(Q24>0,$C24,1) -> 1 | Y24: =IF(R24>0,$C24,1) -> 1 | Z24: =IF(S24>0,$C24,1) -> 1 | AA24: =IF(T24>0,$C24,1) -> 1
A25: Voice Ordering | B25: Premium, Standard | C25: 1.06 | D25: 80000 | E25: =100000*(C25-1)/D25 -> 0.075 | I25: 1 | O25: =H25*$D25 -> 0 | P25: =I25*$D25 -> 80000 | Q25: =J25*$D25 -> 0 | R25: =K25*$D25 -> 0 | S25: =L25*$D25 -> 0 | T25: =M25*$D25 -> 0 | V25: =IF(O25>0,$C25,1) -> 1 | W25: =IF(P25>0,$C25,1) -> 1.06 | X25: =IF(Q25>0,$C25,1) -> 1 | Y25: =IF(R25>0,$C25,1) -> 1 | Z25: =IF(S25>0,$C25,1) -> 1 | AA25: =IF(T25>0,$C25,1) -> 1
A26: Dark Store System | C26: 1.08 | D26: 108000 | E26: =100000*(C26-1)/D26 -> 0.074074074 | J26: 1 | O26: =H26*$D26 -> 0 | P26: =I26*$D26 -> 0 | Q26: =J26*$D26 -> 108000 | R26: =K26*$D26 -> 0 | S26: =L26*$D26 -> 0 | T26: =M26*$D26 -> 0 | V26: =IF(O26>0,$C26,1) -> 1 | W26: =IF(P26>0,$C26,1) -> 1 | X26: =IF(Q26>0,$C26,1) -> 1.08 | Y26: =IF(R26>0,$C26,1) -> 1 | Z26: =IF(S26>0,$C26,1) -> 1 | AA26: =IF(T26>0,$C26,1) -> 1
A27: Rider App | C27: 1.07 | D27: 103500 | E27: =100000*(C27-1)/D27 -> 0.06763285 | K27: 1 | O27: =H27*$D27 -> 0 | P27: =I27*$D27 -> 0 | Q27: =J27*$D27 -> 0 | R27: =K27*$D27 -> 103500 | S27: =L27*$D27 -> 0 | T27: =M27*$D27 -> 0 | V27: =IF(O27>0,$C27,1) -> 1 | W27: =IF(P27>0,$C27,1) -> 1 | X27: =IF(Q27>0,$C27,1) -> 1 | Y27: =IF(R27>0,$C27,1) -> 1.07 | Z27: =IF(S27>0,$C27,1) -> 1 | AA27: =IF(T27>0,$C27,1) -> 1
A28: Demand Forecasting AI | C28: 1.12 | D28: 120000 | E28: =100000*(C28-1)/D28 -> 0.1 | L28: 1 | O28: =H28*$D28 -> 0 | P28: =I28*$D28 -> 0 | Q28: =J28*$D28 -> 0 | R28: =K28*$D28 -> 0 | S28: =L28*$D28 -> 120000 | T28: =M28*$D28 -> 0 | V28: =IF(O28>0,$C28,1) -> 1 | W28: =IF(P28>0,$C28,1) -> 1 | X28: =IF(Q28>0,$C28,1) -> 1 | Y28: =IF(R28>0,$C28,1) -> 1 | Z28: =IF(S28>0,$C28,1) -> 1.12 | AA28: =IF(T28>0,$C28,1) -> 1
A29: Dynamic Pricing | C29: 1.12 | D29: 120000 | E29: =100000*(C29-1)/D29 -> 0.1 | M29: 1 | O29: =H29*$D29 -> 0 | P29: =I29*$D29 -> 0 | Q29: =J29*$D29 -> 0 | R29: =K29*$D29 -> 0 | S29: =L29*$D29 -> 0 | T29: =M29*$D29 -> 120000 | V29: =IF(O29>0,$C29,1) -> 1 | W29: =IF(P29>0,$C29,1) -> 1 | X29: =IF(Q29>0,$C29,1) -> 1 | Y29: =IF(R29>0,$C29,1) -> 1 | Z29: =IF(S29>0,$C29,1) -> 1 | AA29: =IF(T29>0,$C29,1) -> 1.12
A30: Supply Chain Analytics | C30: 1.06 | D30: 80000 | E30: =100000*(C30-1)/D30 -> 0.075 | L30: 1 | O30: =H30*$D30 -> 0 | P30: =I30*$D30 -> 0 | Q30: =J30*$D30 -> 0 | R30: =K30*$D30 -> 0 | S30: =L30*$D30 -> 80000 | T30: =M30*$D30 -> 0 | V30: =IF(O30>0,$C30,1) -> 1 | W30: =IF(P30>0,$C30,1) -> 1 | X30: =IF(Q30>0,$C30,1) -> 1 | Y30: =IF(R30>0,$C30,1) -> 1 | Z30: =IF(S30>0,$C30,1) -> 1.06 | AA30: =IF(T30>0,$C30,1) -> 1
A31: Website Development | B31: Slider | C31: 0.03 | D31: 35000 | E31: =100000*(C31)/D31 -> 0.085714286 | H31: 1 | I31: 2 | J31: 3 | K31: 2 | L31: 3 | M31: 1 | O31: =H31*$D31 -> 35000 | P31: =I31*$D31 -> 70000 | Q31: =J31*$D31 -> 105000 | R31: =K31*$D31 -> 70000 | S31: =L31*$D31 -> 105000 | T31: =M31*$D31 -> 35000 | V31: =1+(O31*$C31/$D31) -> 1.03 | W31: =1+(P31*$C31/$D31) -> 1.06 | X31: =1+(Q31*$C31/$D31) -> 1.09 | Y31: =1+(R31*$C31/$D31) -> 1.06 | Z31: =1+(S31*$C31/$D31) -> 1.09 | AA31: =1+(T31*$C31/$D31) -> 1.03
A32: Total investment/average | B32: Competitive | C32: 0.9 | D32: 1 | V32: =IF(O23<AVERAGE($O$23:$T$23),$C32,$D32) -> 0.9 | W32: =IF(P23<AVERAGE($O$23:$T$23),$C32,$D32) -> 0.9 | X32: =IF(Q23<AVERAGE($O$23:$T$23),$C32,$D32) -> 1 | Y32: =IF(R23<AVERAGE($O$23:$T$23),$C32,$D32) -> 0.9 | Z32: =IF(S23<AVERAGE($O$23:$T$23),$C32,$D32) -> 1 | AA32: =IF(T23<AVERAGE($O$23:$T$23),$C32,$D32) -> 0.9
A36: STEP 4
A37: Sourcing | B37: Applies To | C37: Multiplier | D37: Cost | E37: Ratio
A38: Sustainability 5 star | B38: Premium | C38: 1.2
A39: Sustainability 4.5 star | B39: Premium | C39: 1.1
A40: Sustainability 4 star | B40: Premium | C40: 1
A41: Sustainability 3.5 star | B41: Premium | C41: 0.95
A42: Sustainability 3 star | B42: Premium | C42: 0.9
A43: Sustainability 5 star | B43: Mass | C43: 1.1
A44: Sustainability 4.5 star | B44: Mass | C44: 1.1
A45: Sustainability 4 star | B45: Mass | C45: 1.1
A46: Sustainability 3.5 star | B46: Mass | C46: 1
A47: Sustainability 3 star | B47: Mass | C47: 0.95
A50: STEP 5
A51: Marketing | B51: Applies To | C51: Multiplier | D51: Cost | E51: Ratio | O51: =SUM(O52:O63) -> 165000 | P51: =SUM(P52:P63) -> 360000 | Q51: =SUM(Q52:Q63) -> 355000 | R51: =SUM(R52:R63) -> 320000 | S51: =SUM(S52:S63) -> 306000 | T51: =SUM(T52:T63) -> 190000 | V51: =PRODUCT(V52:V64) -> 1.0487232 | W51: =PRODUCT(W52:W64) -> 1.4055392 | X51: =PRODUCT(X52:X64) -> 1.3681505 | Y51: =PRODUCT(Y52:Y64) -> 1.322231 | Z51: =PRODUCT(Z52:Z64) -> 1.3173888 | AA51: =PRODUCT(AA52:AA64) -> 1.0616112
A52: Google Ads | B52: Slider | C52: 0.02 | D52: 25000 | E52: =100000*(C52)/D52 -> 0.08 | H52: 1 | I52: 2 | J52: 3 | K52: 4 | L52: 2 | M52: 2 | O52: =H52*$D52 -> 25000 | P52: =I52*$D52 -> 50000 | Q52: =J52*$D52 -> 75000 | R52: =K52*$D52 -> 100000 | S52: =L52*$D52 -> 50000 | T52: =M52*$D52 -> 50000 | V52: =1+(O52*$C52/$D52) -> 1.02 | W52: =1+(P52*$C52/$D52) -> 1.04 | X52: =1+(Q52*$C52/$D52) -> 1.06 | Y52: =1+(R52*$C52/$D52) -> 1.08 | Z52: =1+(S52*$C52/$D52) -> 1.04 | AA52: =1+(T52*$C52/$D52) -> 1.04
A53: Facebook Ads | B53: Slider | C53: 0.02 | D53: 20000 | E53: =100000*(C53)/D53 -> 0.1 | H53: 1 | I53: 2 | J53: 1 | K53: 2 | L53: 2 | M53: 3 | O53: =H53*$D53 -> 20000 | P53: =I53*$D53 -> 40000 | Q53: =J53*$D53 -> 20000 | R53: =K53*$D53 -> 40000 | S53: =L53*$D53 -> 40000 | T53: =M53*$D53 -> 60000 | V53: =1+(O53*$C53/$D53) -> 1.02 | W53: =1+(P53*$C53/$D53) -> 1.04 | X53: =1+(Q53*$C53/$D53) -> 1.02 | Y53: =1+(R53*$C53/$D53) -> 1.04 | Z53: =1+(S53*$C53/$D53) -> 1.04 | AA53: =1+(T53*$C53/$D53) -> 1.06
A54: Referral Program | C54: 1.12 | D54: 120000 | E54: =100000*(C54-1)/D54 -> 0.1 | H54: 1 | O54: =H54*$D54 -> 120000 | P54: =I54*$D54 -> 0 | Q54: =J54*$D54 -> 0 | R54: =K54*$D54 -> 0 | S54: =L54*$D54 -> 0 | T54: =M54*$D54 -> 0 | V54: =IF(O54>0,$C54,1) -> 1.12 | W54: =IF(P54>0,$C54,1) -> 1 | X54: =IF(Q54>0,$C54,1) -> 1 | Y54: =IF(R54>0,$C54,1) -> 1 | Z54: =IF(S54>0,$C54,1) -> 1 | AA54: =IF(T54>0,$C54,1) -> 1
A55: First Order Discount | B55: Standard, Basic, Discount | C55: 1.15 | D55: 150000 | E55: =100000*(C55-1)/D55 -> 0.1 | I55: 1 | O55: =H55*$D55 -> 0 | P55: =I55*$D55 -> 150000 | Q55: =J55*$D55 -> 0 | R55: =K55*$D55 -> 0 | S55: =L55*$D55 -> 0 | T55: =M55*$D55 -> 0 | V55: =IF(O55>0,$C55,1) -> 1 | W55: =IF(P55>0,$C55,1) -> 1.15 | X55: =IF(Q55>0,$C55,1) -> 1 | Y55: =IF(R55>0,$C55,1) -> 1 | Z55: =IF(S55>0,$C55,1) -> 1 | AA55: =IF(T55>0,$C55,1) -> 1
A56: Influencer Marketing | B56: Premium, Standard | C56: 1.11 | D56: 110000 | E56: =100000*(C56-1)/D56 -> 0.1 | J56: 1 | O56: =H56*$D56 -> 0 | P56: =I56*$D56 -> 0 | Q56: =J56*$D56 -> 110000 | R56: =K56*$D56 -> 0 | S56: =L56*$D56 -> 0 | T56: =M56*$D56 -> 0 | V56: =IF(O56>0,$C56,1) -> 1 | W56: =IF(P56>0,$C56,1) -> 1 | X56: =IF(Q56>0,$C56,1) -> 1.11 | Y56: =IF(R56>0,$C56,1) -> 1 | Z56: =IF(S56>0,$C56,1) -> 1 | AA56: =IF(T56>0,$C56,1) -> 1
A57: Cashback Option | B57: Standard, Basic, Discount | C57: 1.09 | D57: 95000 | E57: =100000*(C57-1)/D57 -> 0.094736842 | K57: 1 | O57: =H57*$D57 -> 0 | P57: =I57*$D57 -> 0 | Q57: =J57*$D57 -> 0 | R57: =K57*$D57 -> 95000 | S57: =L57*$D57 -> 0 | T57: =M57*$D57 -> 0 | V57: =IF(O57>0,$C57,1) -> 1 | W57: =IF(P57>0,$C57,1) -> 1 | X57: =IF(Q57>0,$C57,1) -> 1 | Y57: =IF(R57>0,$C57,1) -> 1.09 | Z57: =IF(S57>0,$C57,1) -> 1 | AA57: =IF(T57>0,$C57,1) -> 1
A58: Loyalty Program | B58: Premium, Standard | C58: 1.16 | D58: 156000 | E58: =100000*(C58-1)/D58 -> 0.1025641 | L58: 1 | O58: =H58*$D58 -> 0 | P58: =I58*$D58 -> 0 | Q58: =J58*$D58 -> 0 | R58: =K58*$D58 -> 0 | S58: =L58*$D58 -> 156000 | T58: =M58*$D58 -> 0 | V58: =IF(O58>0,$C58,1) -> 1 | W58: =IF(P58>0,$C58,1) -> 1 | X58: =IF(Q58>0,$C58,1) -> 1 | Y58: =IF(R58>0,$C58,1) -> 1 | Z58: =IF(S58>0,$C58,1) -> 1.16 | AA58: =IF(T58>0,$C58,1) -> 1
A59: Push Notifications | C59: 1.07 | D59: 80000 | E59: =100000*(C59-1)/D59 -> 0.0875 | M59: 1 | O59: =H59*$D59 -> 0 | P59: =I59*$D59 -> 0 | Q59: =J59*$D59 -> 0 | R59: =K59*$D59 -> 0 | S59: =L59*$D59 -> 0 | T59: =M59*$D59 -> 80000 | V59: =IF(O59>0,$C59,1) -> 1 | W59: =IF(P59>0,$C59,1) -> 1 | X59: =IF(Q59>0,$C59,1) -> 1 | Y59: =IF(R59>0,$C59,1) -> 1 | Z59: =IF(S59>0,$C59,1) -> 1 | AA59: =IF(T59>0,$C59,1) -> 1.07
A60: Email and SMS | C60: 1.05 | D60: 60000 | E60: =100000*(C60-1)/D60 -> 0.083333333 | L60: 1 | O60: =H60*$D60 -> 0 | P60: =I60*$D60 -> 0 | Q60: =J60*$D60 -> 0 | R60: =K60*$D60 -> 0 | S60: =L60*$D60 -> 60000 | T60: =M60*$D60 -> 0 | V60: =IF(O60>0,$C60,1) -> 1 | W60: =IF(P60>0,$C60,1) -> 1 | X60: =IF(Q60>0,$C60,1) -> 1 | Y60: =IF(R60>0,$C60,1) -> 1 | Z60: =IF(S60>0,$C60,1) -> 1.05 | AA60: =IF(T60>0,$C60,1) -> 1
A61: Credit Card Offers | B61: Premium, Standard | C61: 1.08 | D61: 85000 | E61: =100000*(C61-1)/D61 -> 0.094117647 | K61: 1 | O61: =H61*$D61 -> 0 | P61: =I61*$D61 -> 0 | Q61: =J61*$D61 -> 0 | R61: =K61*$D61 -> 85000 | S61: =L61*$D61 -> 0 | T61: =M61*$D61 -> 0 | V61: =IF(O61>0,$C61,1) -> 1 | W61: =IF(P61>0,$C61,1) -> 1 | X61: =IF(Q61>0,$C61,1) -> 1 | Y61: =IF(R61>0,$C61,1) -> 1.08 | Z61: =IF(S61>0,$C61,1) -> 1 | AA61: =IF(T61>0,$C61,1) -> 1
A62: Corporate Tie-ups | B62: Premium, Standard | C62: 1.14 | D62: 150000 | E62: =100000*(C62-1)/D62 -> 0.093333333 | J62: 1 | O62: =H62*$D62 -> 0 | P62: =I62*$D62 -> 0 | Q62: =J62*$D62 -> 150000 | R62: =K62*$D62 -> 0 | S62: =L62*$D62 -> 0 | T62: =M62*$D62 -> 0 | V62: =IF(O62>0,$C62,1) -> 1 | W62: =IF(P62>0,$C62,1) -> 1 | X62: =IF(Q62>0,$C62,1) -> 1.14 | Y62: =IF(R62>0,$C62,1) -> 1 | Z62: =IF(S62>0,$C62,1) -> 1 | AA62: =IF(T62>0,$C62,1) -> 1
A63: Housing Society | B63: Standard, Basic | C63: 1.13 | D63: 120000 | E63: =100000*(C63-1)/D63 -> 0.10833333 | I63: 1 | O63: =H63*$D63 -> 0 | P63: =I63*$D63 -> 120000 | Q63: =J63*$D63 -> 0 | R63: =K63*$D63 -> 0 | S63: =L63*$D63 -> 0 | T63: =M63*$D63 -> 0 | V63: =IF(O63>0,$C63,1) -> 1 | W63: =IF(P63>0,$C63,1) -> 1.13 | X63: =IF(Q63>0,$C63,1) -> 1 | Y63: =IF(R63>0,$C63,1) -> 1 | Z63: =IF(S63>0,$C63,1) -> 1 | AA63: =IF(T63>0,$C63,1) -> 1
A64: Total investment/average | B64: Competitive | C64: 0.9 | D64: 1 | V64: =IF(O51<AVERAGE($O$51:$T$51),$C64,$D64) -> 0.9 | W64: =IF(P51<AVERAGE($O$51:$T$51),$C64,$D64) -> 1 | X64: =IF(Q51<AVERAGE($O$51:$T$51),$C64,$D64) -> 1 | Y64: =IF(R51<AVERAGE($O$51:$T$51),$C64,$D64) -> 1 | Z64: =IF(S51<AVERAGE($O$51:$T$51),$C64,$D64) -> 1 | AA64: =IF(T51<AVERAGE($O$51:$T$51),$C64,$D64) -> 0.9
A67: STEP 6
A68: Operations HR | B68: Applies To | C68: Multiplier | D68: Cost | E68: Ratio | O68: =SUM(O70:O72) -> 101800 | P68: =SUM(P70:P72) -> 144500 | Q68: =SUM(Q70:Q72) -> 139000 | R68: =SUM(R70:R72) -> 183500 | S68: =SUM(S70:S72) -> 128000 | T68: =SUM(T70:T72) -> 122500 | V68: =PRODUCT(V70:V72) -> 0.97335 | W68: =PRODUCT(W70:W72) -> 0.9405 | X68: =PRODUCT(X70:X72) -> 1.135575 | Y68: =PRODUCT(Y70:Y72) -> 1.30295 | Z68: =PRODUCT(Z70:Z72) -> 1.243725 | AA68: =PRODUCT(AA70:AA72) -> 1.242
A69: Management | B69: Mandatory | C69: 0 | D69: 0 | E69: 0
A70: Corporate Team Size | B70: Choose, Competitive | C70: 0.95 | D70: 1.03 | E70: 1.08 | O70: 50000 | P70: 40000 | Q70: 80000 | R70: 70000 | S70: 60000 | T70: 100000 | V70: =IF(O70=MIN($O$70:$T$70),$C70,IF(O70=MAX($O$70:$T$70),$E70,$D70)) -> 1.03 | W70: =IF(P70=MIN($O$70:$T$70),$C70,IF(P70=MAX($O$70:$T$70),$E70,$D70)) -> 0.95 | X70: =IF(Q70=MIN($O$70:$T$70),$C70,IF(Q70=MAX($O$70:$T$70),$E70,$D70)) -> 1.03 | Y70: =IF(R70=MIN($O$70:$T$70),$C70,IF(R70=MAX($O$70:$T$70),$E70,$D70)) -> 1.03 | Z70: =IF(S70=MIN($O$70:$T$70),$C70,IF(S70=MAX($O$70:$T$70),$E70,$D70)) -> 1.03 | AA70: =IF(T70=MIN($O$70:$T$70),$C70,IF(T70=MAX($O$70:$T$70),$E70,$D70)) -> 1.08
A71: Education Budget/Rider | B71: Slider | C71: 0.05 | D71: 50000 | E71: =100000*(C71)/D71 -> 0.1 | H71: 1 | I71: 2 | J71: 1 | K71: 2 | L71: 1 | M71: 0 | O71: =H71*$D71 -> 50000 | P71: =I71*$D71 -> 100000 | Q71: =J71*$D71 -> 50000 | R71: =K71*$D71 -> 100000 | S71: =L71*$D71 -> 50000 | T71: =M71*$D71 -> 0 | V71: =1+(O71*$C71/$D71) -> 1.05 | W71: =1+(P71*$C71/$D71) -> 1.1 | X71: =1+(Q71*$C71/$D71) -> 1.05 | Y71: =1+(R71*$C71/$D71) -> 1.1 | Z71: =1+(S71*$C71/$D71) -> 1.05 | AA71: =1+(T71*$C71/$D71) -> 1
A72: Rider Bonus Budget | B72: Slider | C72: 0.9 | D72: 1.05 | E72: 1.15 | H72: 0.02 | I72: 0.05 | J72: 0.1 | K72: 0.15 | L72: 0.2 | M72: 0.25 | O72: =H72*H11*$D11 -> 1800 | P72: =I72*I11*$D11 -> 4500 | Q72: =J72*J11*$D11 -> 9000 | R72: =K72*K11*$D11 -> 13500 | S72: =L72*L11*$D11 -> 18000 | T72: =M72*M11*$D11 -> 22500 | V72: =IF(H72<C$73,$C72,IF(H72>$D73,$E72,$D72)) -> 0.9 | W72: =IF(I72<D$73,$C72,IF(I72>$D73,$E72,$D72)) -> 0.9 | X72: =IF(J72<E$73,$C72,IF(J72>$D73,$E72,$D72)) -> 1.05 | Y72: =IF(K72<F$73,$C72,IF(K72>$D73,$E72,$D72)) -> 1.15 | Z72: =IF(L72<G$73,$C72,IF(L72>$D73,$E72,$D72)) -> 1.15 | AA72: =IF(M72<H$73,$C72,IF(M72>$D73,$E72,$D72)) -> 1.15
C73: 0.05 | D73: 0.1
A75: STEP 7
A76: Quality | B76: Choose | H76: 1 | I76: 2 | J76: 3 | K76: 4 | L76: 5 | M76: 5
A77: Sigmoid | B77: Automatic | D77: Category Wise | H77: =100/(1+EXP(-((H76-AVERAGE($H$76:$M$76))/_xlfn.STDEV.S($H$76:$M$76)))) -> 19.327497 | I77: =100/(1+EXP(-((I76-AVERAGE($H$76:$M$76))/_xlfn.STDEV.S($H$76:$M$76)))) -> 30.650784 | J77: =100/(1+EXP(-((J76-AVERAGE($H$76:$M$76))/_xlfn.STDEV.S($H$76:$M$76)))) -> 44.914542 | K77: =100/(1+EXP(-((K76-AVERAGE($H$76:$M$76))/_xlfn.STDEV.S($H$76:$M$76)))) -> 60.066778 | L77: =100/(1+EXP(-((L76-AVERAGE($H$76:$M$76))/_xlfn.STDEV.S($H$76:$M$76)))) -> 73.509349 | M77: =100/(1+EXP(-((M76-AVERAGE($H$76:$M$76))/_xlfn.STDEV.S($H$76:$M$76)))) -> 73.509349
A78: CP Mult | B78: Automatic | D78: 1200 | H78: =VLOOKUP(H76,$A$96:$F$103,6,FALSE) -> 1 | I78: =VLOOKUP(I76,$A$96:$F$103,6,FALSE) -> 1.2 | J78: =VLOOKUP(J76,$A$96:$F$103,6,FALSE) -> 1.4 | K78: =VLOOKUP(K76,$A$96:$F$103,6,FALSE) -> 1.6 | L78: =VLOOKUP(L76,$A$96:$F$103,6,FALSE) -> 1.8 | M78: =VLOOKUP(M76,$A$96:$F$103,6,FALSE) -> 1.8 | O78: =H78*$D78 -> 1200 | P78: =I78*$D78 -> 1440 | Q78: =J78*$D78 -> 1680 | R78: =K78*$D78 -> 1920 | S78: =L78*$D78 -> 2160 | T78: =M78*$D78 -> 2160
A79: SP Mult | B79: Choose | H79: 2 | I79: 2.2 | J79: 2.5 | K79: 2.6 | L79: 2.8 | M79: 3.2 | O79: =O78*H79 -> 2400 | P79: =P78*I79 -> 3168 | Q79: =Q78*J79 -> 4200 | R79: =R78*K79 -> 4992 | S79: =S78*L79 -> 6048 | T79: =T78*M79 -> 6912
A80: SP Mult Base | B80: Automatic | H80: =H78*H79 -> 2 | I80: =I78*I79 -> 2.64 | J80: =J78*J79 -> 3.5 | K80: =K78*K79 -> 4.16 | L80: =L78*L79 -> 5.04 | M80: =M78*M79 -> 5.76
A81: Sigmoid | B81: Automatic | H81: =100/(1+EXP(-((H80-AVERAGE($H$80:$M$80))/_xlfn.STDEV.S($H$80:$M$80)))) -> 21.463556 | I81: =100/(1+EXP(-((I80-AVERAGE($H$80:$M$80))/_xlfn.STDEV.S($H$80:$M$80)))) -> 29.975956 | J81: =100/(1+EXP(-((J80-AVERAGE($H$80:$M$80))/_xlfn.STDEV.S($H$80:$M$80)))) -> 43.895175 | K81: =100/(1+EXP(-((K80-AVERAGE($H$80:$M$80))/_xlfn.STDEV.S($H$80:$M$80)))) -> 55.412946 | L81: =100/(1+EXP(-((L80-AVERAGE($H$80:$M$80))/_xlfn.STDEV.S($H$80:$M$80)))) -> 69.728854 | M81: =100/(1+EXP(-((M80-AVERAGE($H$80:$M$80))/_xlfn.STDEV.S($H$80:$M$80)))) -> 79.237117
A82: Sigmoid New | B82: Automatic | C82: m_0, k | D82: 3.2 | E82: 0.8 | H82: =100/(1+EXP(-$E82*(H80-$D82))) -> 27.687819 | I82: =100/(1+EXP(-$E82*(I80-$D82))) -> 38.983639 | J82: =100/(1+EXP(-$E82*(J80-$D82))) -> 55.971365 | K82: =100/(1+EXP(-$E82*(K80-$D82))) -> 68.308809 | L82: =100/(1+EXP(-$E82*(L80-$D82))) -> 81.336119 | M82: =100/(1+EXP(-$E82*(M80-$D82))) -> 88.574537
A85: Others | V85: =PRODUCT(V86:V88) -> 2.2525 | W85: =PRODUCT(W86:W88) -> 2.2525 | X85: =PRODUCT(X86:X88) -> 2.2525 | Y85: =PRODUCT(Y86:Y88) -> 2.2525 | Z85: =PRODUCT(Z86:Z88) -> 2.2525 | AA85: =PRODUCT(AA86:AA88) -> 2.2525
A86: Focus | B86: Reduce by 0.4 till 1.5 | C86: 2.65 | D86: 1.5 | V86: =$C86 -> 2.65 | W86: =$C86 -> 2.65 | X86: =$C86 -> 2.65 | Y86: =$C86 -> 2.65 | Z86: =$C86 -> 2.65 | AA86: =$C86 -> 2.65
A87: New Player in Segment | C87: 0.85 | D87: 0.95 | E87: 1 | V87: =$C87 -> 0.85 | W87: =$C87 -> 0.85 | X87: =$C87 -> 0.85 | Y87: =$C87 -> 0.85 | Z87: =$C87 -> 0.85 | AA87: =$C87 -> 0.85
A88: R&D | B88: Choose | C88: Based Segment | V88: 1 | W88: 1 | X88: 1 | Y88: 1 | Z88: 1 | AA88: 1
A90: Others
A91: Height Price Prem | B91: Automatic | D91: 80 | E91: 98 | V91: =IF(AND(H$82>$D91,H$82<$E91),1,0) -> 0 | W91: =IF(AND(I82>$D91,I82<$E91),1,0) -> 0 | X91: =IF(AND(J82>$D91,J82<$E91),1,0) -> 0 | Y91: =IF(AND(K82>$D91,K82<$E91),1,0) -> 0 | Z91: =IF(AND(L82>$D91,L82<$E91),1,0) -> 1 | AA91: =IF(AND(M82>$D91,M82<$E91),1,0) -> 1
A92: Height Price Std | B92: Automatic | D92: 65 | E92: 85 | V92: =IF(AND(H$82>$D92,H$82<$E92),1,0) -> 0 | W92: =IF(AND(I$82>$D92,I$82<$E92),1,0) -> 0 | X92: =IF(AND(J$82>$D92,J$82<$E92),1,0) -> 0 | Y92: =IF(AND(K$82>$D92,K$82<$E92),1,0) -> 1 | Z92: =IF(AND(L$82>$D92,L$82<$E92),1,0) -> 1 | AA92: =IF(AND(M$82>$D92,M$82<$E92),1,0) -> 0
A93: Height Price Bas | B93: Automatic | D93: 40 | E93: 70 | V93: =IF(AND(H$82>$D93,H$82<$E93),1,0) -> 0 | W93: =IF(AND(I$82>$D93,I$82<$E93),1,0) -> 0 | X93: =IF(AND(J$82>$D93,J$82<$E93),1,0) -> 1 | Y93: =IF(AND(K$82>$D93,K$82<$E93),1,0) -> 1 | Z93: =IF(AND(L$82>$D93,L$82<$E93),1,0) -> 0 | AA93: =IF(AND(M$82>$D93,M$82<$E93),1,0) -> 0
A94: Height Price Disc | B94: Automatic | D94: 20 | E94: 50 | V94: =IF(AND(H$82>$D94,H$82<$E94),1,0) -> 1 | W94: =IF(AND(I$82>$D94,I$82<$E94),1,0) -> 1 | X94: =IF(AND(J$82>$D94,J$82<$E94),1,0) -> 0 | Y94: =IF(AND(K$82>$D94,K$82<$E94),1,0) -> 0 | Z94: =IF(AND(L$82>$D94,L$82<$E94),1,0) -> 0 | AA94: =IF(AND(M$82>$D94,M$82<$E94),1,0) -> 0
A96: Quality | B96: Premium | C96: Standard | D96: Basic | E96: Discount | F96: CP Mult | G96: Sigmoid
A97: 1 | D97: 1 | E97: 1 | F97: 1 | G97: =100/(1+EXP(-((A97-AVERAGE($A$97:$A$103))/_xlfn.STDEV.S($A$97:$A$103)))) -> 19.961056
A98: 2 | D98: 1 | E98: 1 | F98: 1.2 | G98: =100/(1+EXP(-((A98-AVERAGE($A$97:$A$103))/_xlfn.STDEV.S($A$97:$A$103)))) -> 28.377349
A99: 3 | C99: 1 | D99: 1 | F99: 1.4 | G99: =100/(1+EXP(-((A99-AVERAGE($A$97:$A$103))/_xlfn.STDEV.S($A$97:$A$103)))) -> 38.629571
A100: 4 | B100: 1 | C100: 1 | F100: 1.6 | G100: =100/(1+EXP(-((A100-AVERAGE($A$97:$A$103))/_xlfn.STDEV.S($A$97:$A$103)))) -> 50
A101: 5 | B101: 1 | C101: 1 | F101: 1.8 | G101: =100/(1+EXP(-((A101-AVERAGE($A$97:$A$103))/_xlfn.STDEV.S($A$97:$A$103)))) -> 61.370429
A102: 6 | B102: 1 | C102: 1 | F102: 2 | G102: =100/(1+EXP(-((A102-AVERAGE($A$97:$A$103))/_xlfn.STDEV.S($A$97:$A$103)))) -> 71.622651
A103: 7 | B103: 1 | F103: 2.4 | G103: =100/(1+EXP(-((A103-AVERAGE($A$97:$A$103))/_xlfn.STDEV.S($A$97:$A$103)))) -> 80.038944
A106: Base Points Elasticity | B106: Premium | C106: Standard | D106: Basic | E106: Discount | H106: Points
A107: Selling Price | B107: 0.1 | C107: 0.3 | D107: 0.5 | E107: 0.9 | H107: =100-H81 -> 78.536444 | I107: =100-I81 -> 70.024044 | J107: =100-J81 -> 56.104825 | K107: =100-K81 -> 44.587054 | L107: =100-L81 -> 30.271146 | M107: =100-M81 -> 20.762883
A108: Competitive Quality | B108: 0.8 | C108: 0.6 | D108: 0.4 | E108: 0.2 | H108: =H77 -> 19.327497 | I108: =I77 -> 30.650784 | J108: =J77 -> 44.914542 | K108: =K77 -> 60.066778 | L108: =L77 -> 73.509349 | M108: =M77 -> 73.509349
A109: Actual Quality | B109: 0.9 | C109: 0.6 | D109: 0.3 | E109: 0.1 | H109: =VLOOKUP(H76,$A$96:$G$103,7,FALSE) -> 19.961056 | I109: =VLOOKUP(I76,$A$96:$G$103,7,FALSE) -> 28.377349 | J109: =VLOOKUP(J76,$A$96:$G$103,7,FALSE) -> 38.629571 | K109: =VLOOKUP(K76,$A$96:$G$103,7,FALSE) -> 50 | L109: =VLOOKUP(L76,$A$96:$G$103,7,FALSE) -> 61.370429 | M109: =VLOOKUP(M76,$A$96:$G$103,7,FALSE) -> 61.370429
A110: Height Price | B110: 0.2 | C110: 0.5 | D110: 0.6 | E110: 0.8 | H110: =100-H82 -> 72.312181 | I110: =100-I82 -> 61.016361 | J110: =100-J82 -> 44.028635 | K110: =100-K82 -> 31.691191 | L110: =100-L82 -> 18.663881 | M110: =100-M82 -> 11.425463
A114: Base SP
A115: Premium | K115: =K107*$B107 -> 4.4587054 | L115: =L107*$B107 -> 3.0271146 | M115: =M107*$B107 -> 2.0762883
A116: Standard | J116: =J107*$C107 -> 16.831448 | K116: =K107*$C107 -> 13.376116 | L116: =L107*$C107 -> 9.0813438 | M116: =M107*$C107 -> 6.228865
A117: Basic | H117: =H107*$D107 -> 39.268222 | I117: =I107*$D107 -> 35.012022 | J117: =J107*$D107 -> 28.052413
A118: Discount | H118: =H107*$E107 -> 70.6828 | I118: =I107*$E107 -> 63.02164
A120: Base Competitive Quality
A121: Premium | K121: =K108*$B108 -> 48.053422 | L121: =L108*$B108 -> 58.807479 | M121: =M108*$B108 -> 58.807479
A122: Standard | J122: =J108*$C108 -> 26.948725 | K122: =K108*$C108 -> 36.040067 | L122: =L108*$C108 -> 44.10561 | M122: =M108*$C108 -> 44.10561
...

Sheet Supplier
E1: ORDER (WK) - 4 time to the supplier | F1: 500 | I1: 800 | R1: For all products/all category (sum) for round 1
E2: WEEK1 | F2: WEEK2 | G2: WEEK3 | H2: WEEK4 | I2: WEEK5 | J2: WEEK6 | K2: WEEK7 | L2: WEEK8 | M2: WEEK9 | O2: Starting Inventory | P2: New Inventory | Q2: Total invwnrtory | R2: Demand | S2: Actually Sold | T2: Ending inventory | U2: Wasted demand
B3: Supplier | E3: 0 | F3: 500 | G3: 500 | H3: 500 | I3: 500 | J3: 800 | K3: 800 | L3: 800 | M3: 800 | N3: week1 | O3: 0 | R3: =2400/4 -> 600 | S3: 0 | U3: 600
F4: 0.85 | G4: 0.88 | H4: 0.9 | I4: 0.88 | N4: week2 | P4: 425 | Q4: =O4+P4 -> 425 | R4: 600 | S4: 425 | T4: 0 | U4: 175
B5: Delivery Time | C5: 1 week | F5: =F3*F4 -> 425 | G5: =G3*G4 -> 440 | H5: =H3*H4 -> 450 | I5: =I3*I4 -> 440 | N5: week3 | P5: 440 | Q5: =O5+P5 -> 440 | R5: 600 | S5: 440 | T5: 0 | U5: 160
B6: Reliability | C6: 4 star | N6: week4 | P6: 450 | Q6: =O6+P6 -> 450 | R6: 600 | S6: 450 | T6: 0 | U6: 140
I7: 800 | J7: 800 | K7: 800 | L7: 800 | N7: week5 | P7: =440+760 -> 1200 | Q7: =O7+P7 -> 1200 | R7: =2800/4 -> 700 | S7: 700 | T7: 500 | U7: 0
A8: Reliability | B8: 5 | C8: 4.5 | D8: 4 | I8: 0.95 | J8: 0.98 | K8: 0.98 | L8: 1 | N8: week6 | O8: 500 | P8: 784 | Q8: =O8+P8 -> 1284 | R8: =2800/4 -> 700 | S8: 700 | T8: =Q8-R8 -> 584 | U8: 0
A9: Final | B9: 95-100% | C9: 90-95% | D9: 85-90% | I9: =I7*I8 -> 760 | J9: =J7*J8 -> 784 | K9: =K7*K8 -> 784 | L9: =L7*L8 -> 800 | N9: week7 | O9: =T8 -> 584 | P9: 784 | Q9: =O9+P9 -> 1368 | R9: =2800/4 -> 700 | S9: 700 | T9: =Q9-R9 -> 668 | U9: 0
A10: Random | N10: week8 | O10: =T9 -> 668 | P10: 800 | Q10: =O10+P10 -> 1468 | R10: =2800/4 -> 700 | S10: 700 | T10: =Q10-R10 -> 768 | U10: 0
B13: Delivery Time | C13: Instant | Q13: premium | R13: basic
B14: Reliability | C14: 5 star | P14: food | Q14: 100 | R14: 150
P15: electronics | Q15: 200 | R15: 150
Q17: =Q14/600 -> 0.16666667 | R17: =R14/600 -> 0.25
Q18: =Q15/600 -> 0.33333333 | R18: =R15/600 -> 0.25
P21: actual sold | Q21: =Q17*425 -> 70.833333 | R21: =R17*425 -> 106.25
Q22: =Q18*425 -> 141.66667 | R22: =R18*425 -> 106.25

Sheet Setup
A1: QUICK COMMERCE - FINANCIAL MODEL SETUP
A3: Player Name: | B3: Player 1
A4: Round: | B4: 1
A6: INITIAL CAPITAL
A8: Equity Investment | B8: 500000
A9: Loan Amount | B9: 300000
A10: Interest Rate (Annual) | B10: 0.12
A11: Total Capital | B11: =B8+B9 -> 800000
A13: GAME PARAMETERS
A15: Base Orders per Day | B15: 100
A16: Days per Month | B16: 30

Sheet Inputs
A1: GAME INPUTS - PLAYER DECISIONS
A3: Enter all game decisions here (Blue cells)
A5: CATEGORY MULTIPLIERS
C6: Month 1 | D6: Month 2 | E6: Month 3
A7: Quality Multiplier | C7: 1.15 | D7: 1.18 | E7: 1.22
A9: TOTAL INVESTMENTS
A10: Fleet Investments | C10: 165000
A11: Technology Investments | C11: 140000
A12: Marketing Spend | C12: 165000 | D12: 165000 | E12: 165000
A13: HR Costs | C13: 144500 | D13: 144500 | E13: 144500

Sheet P&L
A1: INCOME STATEMENT
A2: Player: | B2: =Setup!B3 -> Player 1
A4: Line Item | C4: Month 1 | D4: Month 2 | E4: Month 3
A6: REVENUE
A7: Premium Segment | C7: =Setup!$B$15*Setup!$B$16*12*Inputs!C$7 -> 41400 | D7: =Setup!$B$15*Setup!$B$16*12*Inputs!D$7*1.05 -> 44604 | E7: =Setup!$B$15*Setup!$B$16*12*Inputs!E$7*1.08 -> 47433.6
A8: Standard Segment | C8: =Setup!$B$15*Setup!$B$16*10*Inputs!C$7 -> 34500 | D8: =Setup!$B$15*Setup!$B$16*10*Inputs!D$7*1.05 -> 37170 | E8: =Setup!$B$15*Setup!$B$16*10*Inputs!E$7*1.08 -> 39528
A9: Basic Segment | C9: =Setup!$B$15*Setup!$B$16*8*Inputs!C$7 -> 27600 | D9: =Setup!$B$15*Setup!$B$16*8*Inputs!D$7*1.05 -> 29736 | E9: =Setup!$B$15*Setup!$B$16*8*Inputs!E$7*1.08 -> 31622.4
A10: Discount Segment | C10: =Setup!$B$15*Setup!$B$16*6*Inputs!C$7 -> 20700 | D10: =Setup!$B$15*Setup!$B$16*6*Inputs!D$7*1.05 -> 22302 | E10: =Setup!$B$15*Setup!$B$16*6*Inputs!E$7*1.08 -> 23716.8
A11: Total Revenue | C11: =SUM(C7:C10) -> 124200 | D11: =SUM(D7:D10) -> 133812 | E11: =SUM(E7:E10) -> 142300.8
A13: COST OF SALES
A14: Cost of Goods Sold (40%) | C14: =C11*0.4 -> 49680 | D14: =D11*0.4 -> 53524.8 | E14: =E11*0.4 -> 56920.32
A15: Delivery & Packaging | C15: =C11*0.15 -> 18630 | D15: =D11*0.15 -> 20071.8 | E15: =E11*0.15 -> 21345.12
A16: Total Cost of Sales | C16: =SUM(C14:C15) -> 68310 | D16: =SUM(D14:D15) -> 73596.6 | E16: =SUM(E14:E15) -> 78265.44
A17: GROSS PROFIT | C17: =C11-C16 -> 55890 | D17: =D11-D16 -> 60215.4 | E17: =E11-E16 -> 64035.36
A19: OPERATING EXPENSES
A20: Fleet Costs | C20: =Inputs!C9/12 -> 0 | D20: =Inputs!C9/12 -> 0 | E20: =Inputs!C9/12 -> 0
A21: Technology Costs | C21: =Inputs!C10/12 -> 13750 | D21: =Inputs!C10/12 -> 13750 | E21: =Inputs!C10/12 -> 13750
A22: Marketing Expenses | C22: =Inputs!C11 -> 140000 | D22: =Inputs!D11 -> 0 | E22: =Inputs!E11 -> 0
A23: HR & Operations | C23: =Inputs!C12 -> 165000 | D23: =Inputs!D12 -> 165000 | E23: =Inputs!E12 -> 165000
A24: Rent & Utilities | C24: 25000 | D24: 25000 | E24: 25000
A25: Total Operating Expenses | C25: =SUM(C20:C24) -> 343750 | D25: =SUM(D20:D24) -> 203750 | E25: =SUM(E20:E24) -> 203750
A26: EBITDA | C26: =C17-C25 -> -287860 | D26: =D17-D25 -> -143534.6 | E26: =E17-E25 -> -139714.64
A27: Depreciation & Amortization | C27: 5000 | D27: 5000 | E27: 5000
A28: EBIT | C28: =C26-C27 -> -292860 | D28: =D26-D27 -> -148534.6 | E28: =E26-E27 -> -144714.64
A29: Interest Expense | C29: =Setup!$B$9*Setup!$B$10/12 -> 3000 | D29: =Setup!$B$9*Setup!$B$10/12 -> 3000 | E29: =Setup!$B$9*Setup!$B$10/12 -> 3000
A30: NET INCOME | C30: =C28-C29 -> -295860 | D30: =D28-D29 -> -151534.6 | E30: =E28-E29 -> -147714.64

Sheet Balance Sheet
A1: BALANCE SHEET
A2: Player: | B2: =Setup!B3 -> Player 1
A4: Account | B4: Beginning | C4: Month 1 | D4: Month 2 | E4: Month 3
A6: ASSETS
A7: Current Assets
A8: Cash | B8: =Setup!B11 -> 800000 | C8: =B8+CashFlow!C30 -> 800000 | D8: =C8+CashFlow!D30 -> 800000 | E8: =D8+CashFlow!E30 -> 800000
A9: Accounts Receivable | B9: 0 | C9: 25000 | D9: 28000 | E9: 32000
A10: Inventory | B10: 50000 | C10: 55000 | D10: 58000 | E10: 62000
A11: Total Current Assets | B11: =SUM(B8:B10) -> 850000 | C11: =SUM(C8:C10) -> 880000 | D11: =SUM(D8:D10) -> 886000 | E11: =SUM(E8:E10) -> 894000
A13: Fixed Assets
A14: Property & Equipment | B14: 100000 | C14: 100000 | D14: 100000 | E14: 100000
A15: Less: Accum. Depreciation | B15: 0 | C15: -5000 | D15: -10000 | E15: -15000
A16: Intangible Assets | B16: 50000 | C16: 50000 | D16: 50000 | E16: 50000
A17: Total Fixed Assets | B17: =SUM(B13:B15) -> 100000 | C17: =SUM(C13:C15) -> 95000 | D17: =SUM(D13:D15) -> 90000 | E17: =SUM(E13:E15) -> 85000
A18: TOTAL ASSETS | B18: =B11+B17 -> 950000 | C18: =C11+C17 -> 975000 | D18: =D11+D17 -> 976000 | E18: =E11+E17 -> 979000
A20: LIABILITIES & EQUITY
A21: Current Liabilities
A22: Accounts Payable | B22: 30000 | C22: 35000 | D22: 38000 | E22: 42000
A23: Accrued Expenses | B23: 15000 | C23: 18000 | D23: 20000 | E23: 22000
A24: Total Current Liabilities | B24: =SUM(B21:B22) -> 30000 | C24: =SUM(C21:C22) -> 35000 | D24: =SUM(D21:D22) -> 38000 | E24: =SUM(E21:E22) -> 42000
A26: Long-term Liabilities
A27: Long-term Debt | B27: =Setup!B9 -> 300000 | C27: =Setup!B9 -> 300000 | D27: =Setup!B9 -> 300000 | E27: =Setup!B9 -> 300000
A28: Total Liabilities | B28: =B24+B27 -> 330000 | C28: =C24+C27 -> 335000 | D28: =D24+D27 -> 338000 | E28: =E24+E27 -> 342000
A30: Equity
A31: Share Capital | B31: =Setup!B8 -> 500000 | C31: =Setup!B8 -> 500000 | D31: =Setup!B8 -> 500000 | E31: =Setup!B8 -> 500000
A32: Retained Earnings | B32: 0 | C32: ='P&L'!C30 -> -295860 | D32: =C32+'P&L'!D30 -> -447394.6 | E32: =D32+'P&L'!E30 -> -595109.24
A33: Total Equity | B33: =B31+B32 -> 500000 | C33: =C31+C32 -> 204140 | D33: =D31+D32 -> 52605.4 | E33: =E31+E32 -> -95109.24
A34: TOTAL LIABILITIES & EQUITY | B34: =B28+B33 -> 830000 | C34: =C28+C33 -> 539140 | D34: =D28+D33 -> 390605.4 | E34: =E28+E33 -> 246890.76
A36: BALANCE CHECK (Should be 0) | B36: =B18-B34 -> 120000 | C36: =C18-C34 -> 435860 | D36: =D18-D34 -> 585394.6 | E36: =E18-E34 -> 732109.24

Sheet CashFlow
A1: CASH FLOW STATEMENT
A2: Player: | B2: =Setup!B3 -> Player 1
A4: Activity | C4: Month 1 | D4: Month 2 | E4: Month 3
A6: OPERATING ACTIVITIES
A7: Net Income | C7: ='P&L'!C30 -> -295860 | D7: ='P&L'!D30 -> -151534.6 | E7: ='P&L'!E30 -> -147714.64
A8: Add: Depreciation | C8: 5000 | D8: 5000 | E8: 5000
A9: (Increase) in AR | C9: -25000 | D9: -3000 | E9: -4000
A10: (Increase) in Inventory | C10: -5000 | D10: -3000 | E10: -4000
A11: Increase in AP | C11: 5000 | D11: 3000 | E11: 4000
A12: Increase in Accrued Exp | C12: 3000 | D12: 2000 | E12: 2000
A13: Net Cash from Operations | C13: =SUM(C7:C12) -> -312860 | D13: =SUM(D7:D12) -> -147534.6 | E13: =SUM(E7:E12) -> -144714.64
A15: INVESTING ACTIVITIES
A16: Equipment Purchases | C16: 0 | D16: 0 | E16: 0
A17: Technology Investments | C17: -10000 | D17: -5000 | E17: -8000
A18: Net Cash from Investing | C18: =SUM(C16:C17) -> -10000 | D18: =SUM(D16:D17) -> -5000 | E18: =SUM(E16:E17) -> -8000
A20: FINANCING ACTIVITIES
A21: Equity Proceeds | C21: 0 | D21: 0 | E21: 0
A22: Loan Proceeds/(Repayment) | C22: 0 | D22: 0 | E22: 0
A23: Net Cash from Financing | C23: =SUM(C21:C22) -> 0 | D23: =SUM(D21:D22) -> 0 | E23: =SUM(E21:E22) -> 0
A25: NET CHANGE IN CASH | C25: =C13+C18+C23 -> -322860 | D25: =D13+D18+D23 -> -152534.6 | E25: =E13+E18+E23 -> -152714.64
A27: Cash - Beginning | C27: =Setup!B11 -> 800000 | D27: =C28 -> 477140 | E27: =D28 -> 324605.4
A28: Cash - Ending | C28: =C27+C25 -> 477140 | D28: =D27+D25 -> 324605.4 | E28: =E27+E25 -> 171890.76
